mirrormaker/__init__.py
mirrormaker/github.py
mirrormaker/gitlab.py
mirrormaker/mirrormaker.py
gitlab_mirror_maker-0.4.1.dist-info/entry_points.txt
gitlab_mirror_maker-0.4.1.dist-info/WHEEL
gitlab_mirror_maker-0.4.1.dist-info/METADATA
gitlab_mirror_maker-0.4.1.dist-info/RECORD
